llmrankers/__init__.py
llmrankers/listwise.py
llmrankers/pairwise.py
llmrankers/pointwise.py
llmrankers/rankers.py
llmrankers/setwise.py
llm_rankers-0.0.1.dist-info/LICENSE
llm_rankers-0.0.1.dist-info/METADATA
llm_rankers-0.0.1.dist-info/WHEEL
llm_rankers-0.0.1.dist-info/top_level.txt
llm_rankers-0.0.1.dist-info/RECORD
