Metadata-Version: 2.1
Name: llm-rankers
Version: 0.0.1
Summary: Pointwise, Listwise, Pairwise and Setwise Document Ranking with Large Language Models.
Home-page: https://github.com/ielab/llm-rankers
Author: Shengyao Zhuang
Author-email: s.zhuang@uq.edu.au
License: Apache 2.0
Requires-Python: >=3.8
License-File: LICENSE
Requires-Dist: transformers >=4.31.0
Requires-Dist: openai >=0.27.10
Requires-Dist: tiktoken >=0.4.0
Requires-Dist: accelerate >=0.22.0
